mat3ra/__init__.py
mat3ra/standata/__init__.py
mat3ra/standata/applications.py
mat3ra/standata/base.py
mat3ra/standata/materials.py
mat3ra/standata/model_tree.py
mat3ra/standata/subworkflows.py
mat3ra/standata/workflows.py
mat3ra/standata/build/__init__.py
mat3ra/standata/build/builder.py
mat3ra/standata/build/cli.py
mat3ra/standata/data/__init__.py
mat3ra/standata/data/applications.py
mat3ra/standata/data/materials.py
mat3ra/standata/data/methods.py
mat3ra/standata/data/model_tree.py
mat3ra/standata/data/models.py
mat3ra/standata/data/models_tree_config_by_application.py
mat3ra/standata/data/properties.py
mat3ra/standata/data/subworkflows.py
mat3ra/standata/data/workflows.py
mat3ra/standata/workflow/base.py
mat3ra_standata-2026.1.24.post0.dist-info/licenses/LICENSE.md
mat3ra_standata-2026.1.24.post0.dist-info/METADATA
mat3ra_standata-2026.1.24.post0.dist-info/WHEEL
mat3ra_standata-2026.1.24.post0.dist-info/entry_points.txt
mat3ra_standata-2026.1.24.post0.dist-info/top_level.txt
mat3ra_standata-2026.1.24.post0.dist-info/RECORD
