Metadata-Version: 2.4
Name: mat3ra-standata
Version: 2026.1.24.post0
Summary: Standard data for digital Materials R&D.
Author-email: "Exabyte Inc." <info@mat3ra.com>
License: # LICENSE
Classifier: Programming Language :: Python
Classifier: Programming Language :: Python :: 3
Classifier: Development Status :: 3 - Alpha
Classifier: Topic :: Software Development
Requires-Python: >=3.8
License-File: LICENSE.md
Requires-Dist: pyyaml
Requires-Dist: pandas
Requires-Dist: typer
Requires-Dist: pydantic
Provides-Extra: dev
Requires-Dist: pre-commit; extra == "dev"
Requires-Dist: black; extra == "dev"
Requires-Dist: ruff; extra == "dev"
Requires-Dist: isort; extra == "dev"
Requires-Dist: mypy; extra == "dev"
Requires-Dist: pip-tools; extra == "dev"
Requires-Dist: express-py; extra == "dev"
Provides-Extra: tests
Requires-Dist: coverage[toml]>=5.3; extra == "tests"
Requires-Dist: pytest; extra == "tests"
Requires-Dist: pytest-cov; extra == "tests"
Requires-Dist: gradio; extra == "tests"
Requires-Dist: pydantic; extra == "tests"
Requires-Dist: mat3ra-esse; extra == "tests"
Requires-Dist: mat3ra-utils; extra == "tests"
Provides-Extra: all
Requires-Dist: mat3ra-standata[tests]; extra == "all"
Requires-Dist: mat3ra-standata[dev]; extra == "all"
Dynamic: license-file
